royston/__init__.py
royston/royston copy.py
royston/royston.py
royston/tc_overlap_strategy.py
royston/trend_cluster.py
royston/trend_cluster_strategy.py
royston/util.py
royston-0.0.19.dist-info/entry_points.txt
royston-0.0.19.dist-info/LICENSE
royston-0.0.19.dist-info/WHEEL
royston-0.0.19.dist-info/METADATA
royston-0.0.19.dist-info/RECORD
