Metadata-Version: 2.1
Name: royston
Version: 0.0.19
Summary: A real time trend detection algorithm
Author: Ian Read
Author-email: ianharveyread@gmail.com
Requires-Python: >=3.8,<4.0
Classifier: Programming Language :: Python :: 3
Classifier: Programming Language :: Python :: 3.8
Classifier: Programming Language :: Python :: 3.9
Requires-Dist: coverage (>=5.5,<6.0)
Requires-Dist: dateparser (>=1.0.0,<2.0.0)
Requires-Dist: nltk (>=3.6.5,<4.0.0)
Requires-Dist: python-dateutil (>=2.8.1,<3.0.0)
Requires-Dist: pytz (>=2021.1,<2022.0)
Requires-Dist: twine (>=3.4.2,<4.0.0)
